py_nucflag/__init__.py
py_nucflag/__init__.pyi
py_nucflag/py.typed
py_nucflag/py_nucflag.cpython-311-x86_64-linux-gnu.so
py_nucflag-0.1.7.dist-info/METADATA
py_nucflag-0.1.7.dist-info/WHEEL
py_nucflag-0.1.7.dist-info/licenses/LICENSE
py_nucflag-0.1.7.dist-info/RECORD
