Metadata-Version: 2.4
Name: py_nucflag
Version: 0.1.7
Classifier: Programming Language :: Rust
Classifier: Programming Language :: Python :: Implementation :: CPython
Classifier: Programming Language :: Python :: Implementation :: PyPy
Requires-Dist: polars
License-File: LICENSE
Requires-Python: >=3.8
